LICENSE.txt
MANIFEST.in
README.rst
setup.cfg
setup.py
pyactivetwo/__init__.py
pyactivetwo/pyactivetwo.py
pyactivetwo.egg-info/PKG-INFO
pyactivetwo.egg-info/SOURCES.txt
pyactivetwo.egg-info/dependency_links.txt
pyactivetwo.egg-info/not-zip-safe
pyactivetwo.egg-info/requires.txt
pyactivetwo.egg-info/top_level.txt