Metadata-Version: 1.1
Name: pyactivetwo
Version: 0.1
Summary: Python library for reading signal from BioSemi ActiveTwo EEG device
Home-page: http://github.com/kuz/pyactivetwo
Author: Ilya Kuzovkin
Author-email: ilya.kuzovkin@gmail.com
License: MIT
Keywords: eeg signal biosemi activetwo
Platform: UNKNOWN
Classifier: Development Status :: 3 - Alpha
Classifier: Programming Language :: Python
